{
  "bundleVersion": 1,
  "sampleId": "synthetic-0195",
  "orgId": null,
  "projectId": "demo-project",
  "scenarioId": null,
  "diff": {
    "scenario": "about",
    "viewport": "desktop",
    "browser": "chromium",
    "status": "fail",
    "misMatchPercentage": 19.066963461485958,
    "diffPixels": 219651.0,
    "totalPixels": 1152000.0,
    "dimensions": {
      "width": 1280.0,
      "height": 900.0
    },
    "hasContentRules": false,
    "shiftRegions": null,
    "hasShift": null,
    "elementResults": [
      {
        "selector": "header nav",
        "tag": "nav",
        "ariaLabel": null,
        "semanticLabel": "main navigation",
        "bbox": {
          "x": 0.0,
          "y": 0.0,
          "width": 1280.0,
          "height": 226.0
        },
        "status": "visual_change",
        "mode": "strict",
        "diffPixelCount": null,
        "diffPercentage": 78.99728414015472,
        "dimensionDelta": null,
        "positionDelta": null,
        "appliedRuleId": null,
        "matchConfidence": 0.9584024052694189
      },
      {
        "selector": "footer",
        "tag": "footer",
        "ariaLabel": null,
        "semanticLabel": null,
        "bbox": {
          "x": 0.0,
          "y": 820.0,
          "width": 1280.0,
          "height": 80.0
        },
        "status": "unchanged",
        "mode": "strict",
        "diffPixelCount": null,
        "diffPercentage": null,
        "dimensionDelta": null,
        "positionDelta": null,
        "appliedRuleId": null,
        "matchConfidence": 1.0
      }
    ],
    "blockResults": null,
    "ignoredPixels": null,
    "effectiveTotalPixels": null,
    "staleRules": null,
    "aiAnalysis": null,
    "baselineHeight": 900.0,
    "diffBBox": {
      "x": 0.0,
      "y": 0.0,
      "width": 1280.0,
      "height": 226.0
    }
  },
  "images": {
    "baselinePng": null,
    "testPng": null,
    "diffPng": "fixtures/images/synthetic-0195_diff.png",
    "baselineDomMap": null,
    "testDomMap": null
  },
  "runContext": {
    "runId": "run-synthetic-0195",
    "createdAt": "2026-01-09T03:00:00Z",
    "trigger": "ci",
    "environmentId": null,
    "pageType": null,
    "envIsProd": true,
    "ci": {
      "commitSha": "feb9fe3b363debee",
      "branch": "feature/394",
      "prNumber": null,
      "prTitle": null,
      "isMainBranch": true,
      "jiraKey": null
    },
    "siblingResults": [
      {
        "scenario": "about",
        "viewport": "desktop",
        "browser": "firefox",
        "status": "fail",
        "misMatchPercentage": 18.279264020974768,
        "diffPixels": 1000.0,
        "totalPixels": 1152000.0,
        "dimensions": {
          "width": 1280.0,
          "height": 900.0
        },
        "hasContentRules": false,
        "shiftRegions": null,
        "hasShift": null,
        "elementResults": null,
        "blockResults": null,
        "ignoredPixels": null,
        "effectiveTotalPixels": null,
        "staleRules": null,
        "aiAnalysis": null,
        "baselineHeight": null,
        "diffBBox": null
      },
      {
        "scenario": "about",
        "viewport": "desktop",
        "browser": "webkit",
        "status": "fail",
        "misMatchPercentage": 17.441318409649192,
        "diffPixels": 1000.0,
        "totalPixels": 1152000.0,
        "dimensions": {
          "width": 1280.0,
          "height": 900.0
        },
        "hasContentRules": false,
        "shiftRegions": null,
        "hasShift": null,
        "elementResults": null,
        "blockResults": null,
        "ignoredPixels": null,
        "effectiveTotalPixels": null,
        "staleRules": null,
        "aiAnalysis": null,
        "baselineHeight": null,
        "diffBBox": null
      },
      {
        "scenario": "home",
        "viewport": "desktop",
        "browser": "chromium",
        "status": "pass",
        "misMatchPercentage": 0.0,
        "diffPixels": 0.0,
        "totalPixels": 1152000.0,
        "dimensions": {
          "width": 1280.0,
          "height": 900.0
        },
        "hasContentRules": false,
        "shiftRegions": null,
        "hasShift": null,
        "elementResults": null,
        "blockResults": null,
        "ignoredPixels": null,
        "effectiveTotalPixels": null,
        "staleRules": null,
        "aiAnalysis": null,
        "baselineHeight": null,
        "diffBBox": null
      },
      {
        "scenario": "pricing",
        "viewport": "desktop",
        "browser": "chromium",
        "status": "pass",
        "misMatchPercentage": 0.0,
        "diffPixels": 0.0,
        "totalPixels": 1152000.0,
        "dimensions": {
          "width": 1280.0,
          "height": 900.0
        },
        "hasContentRules": false,
        "shiftRegions": null,
        "hasShift": null,
        "elementResults": null,
        "blockResults": null,
        "ignoredPixels": null,
        "effectiveTotalPixels": null,
        "staleRules": null,
        "aiAnalysis": null,
        "baselineHeight": null,
        "diffBBox": null
      },
      {
        "scenario": "blog",
        "viewport": "desktop",
        "browser": "chromium",
        "status": "fail",
        "misMatchPercentage": 12.237983626971758,
        "diffPixels": 1000.0,
        "totalPixels": 1152000.0,
        "dimensions": {
          "width": 1280.0,
          "height": 900.0
        },
        "hasContentRules": false,
        "shiftRegions": null,
        "hasShift": null,
        "elementResults": null,
        "blockResults": null,
        "ignoredPixels": null,
        "effectiveTotalPixels": null,
        "staleRules": null,
        "aiAnalysis": null,
        "baselineHeight": null,
        "diffBBox": {
          "x": 0.0,
          "y": 0.0,
          "width": 1280.0,
          "height": 226.0
        }
      },
      {
        "scenario": "contact",
        "viewport": "desktop",
        "browser": "chromium",
        "status": "pass",
        "misMatchPercentage": 0.0,
        "diffPixels": 0.0,
        "totalPixels": 1152000.0,
        "dimensions": {
          "width": 1280.0,
          "height": 900.0
        },
        "hasContentRules": false,
        "shiftRegions": null,
        "hasShift": null,
        "elementResults": null,
        "blockResults": null,
        "ignoredPixels": null,
        "effectiveTotalPixels": null,
        "staleRules": null,
        "aiAnalysis": null,
        "baselineHeight": null,
        "diffBBox": null
      }
    ],
    "scenarioConfig": null
  },
  "intentSignals": {
    "github": {
      "commitChangedSinceBaseline": true,
      "prFilesChanged": 32,
      "uiFilesChanged": true,
      "cssLinesChanged": 477,
      "prTitleType": "feat",
      "prHasDesignLabel": true,
      "changedFilesMatchPage": true
    },
    "jira": {
      "jiraKeyPresent": true,
      "jiraIssueIsStory": false,
      "jiraIssueIsBug": false,
      "jiraHasDesignLabel": true
    },
    "figma": null
  },
  "history": [
    {
      "runId": "hist-0",
      "createdAt": "2025-12-30T03:00:00Z",
      "misMatchPercentage": 0.20210942618650507,
      "status": "pass",
      "verdict": null,
      "diffBBox": null
    },
    {
      "runId": "hist-1",
      "createdAt": "2025-12-31T03:00:00Z",
      "misMatchPercentage": 0.07476588131548895,
      "status": "pass",
      "verdict": null,
      "diffBBox": null
    },
    {
      "runId": "hist-2",
      "createdAt": "2026-01-01T03:00:00Z",
      "misMatchPercentage": 0.1722368887013457,
      "status": "pass",
      "verdict": null,
      "diffBBox": null
    },
    {
      "runId": "hist-3",
      "createdAt": "2026-01-02T03:00:00Z",
      "misMatchPercentage": 0.9357059086761251,
      "status": "fail",
      "verdict": null,
      "diffBBox": null
    },
    {
      "runId": "hist-4",
      "createdAt": "2026-01-03T03:00:00Z",
      "misMatchPercentage": 0.6500009575841249,
      "status": "pass",
      "verdict": null,
      "diffBBox": null
    },
    {
      "runId": "hist-5",
      "createdAt": "2026-01-04T03:00:00Z",
      "misMatchPercentage": 0.41387373952756884,
      "status": "fail",
      "verdict": null,
      "diffBBox": null
    },
    {
      "runId": "hist-6",
      "createdAt": "2026-01-05T03:00:00Z",
      "misMatchPercentage": 0.7526360189775249,
      "status": "pass",
      "verdict": null,
      "diffBBox": null
    },
    {
      "runId": "hist-7",
      "createdAt": "2026-01-06T03:00:00Z",
      "misMatchPercentage": 0.961483968880863,
      "status": "fail",
      "verdict": null,
      "diffBBox": null
    },
    {
      "runId": "hist-8",
      "createdAt": "2026-01-07T03:00:00Z",
      "misMatchPercentage": 0.16521700160993152,
      "status": "pass",
      "verdict": null,
      "diffBBox": null
    },
    {
      "runId": "hist-9",
      "createdAt": "2026-01-08T03:00:00Z",
      "misMatchPercentage": 0.46430450109322424,
      "status": "pass",
      "verdict": null,
      "diffBBox": null
    }
  ],
  "label": {
    "verdict": "intentional_redesign",
    "verdictSource": "synthetic",
    "verdictAt": null
  }
}