{
  "bundleVersion": 1,
  "sampleId": "synthetic-0273",
  "orgId": null,
  "projectId": "demo-project",
  "scenarioId": null,
  "diff": {
    "scenario": "contact",
    "viewport": "desktop",
    "browser": "chromium",
    "status": "fail",
    "misMatchPercentage": 22.892928373509402,
    "diffPixels": 263726.0,
    "totalPixels": 1152000.0,
    "dimensions": {
      "width": 1280.0,
      "height": 900.0
    },
    "hasContentRules": false,
    "shiftRegions": null,
    "hasShift": null,
    "elementResults": [
      {
        "selector": "header nav",
        "tag": "nav",
        "ariaLabel": null,
        "semanticLabel": "main navigation",
        "bbox": {
          "x": 0.0,
          "y": 0.0,
          "width": 1280.0,
          "height": 226.0
        },
        "status": "visual_change",
        "mode": "strict",
        "diffPixelCount": null,
        "diffPercentage": 42.93183155876467,
        "dimensionDelta": null,
        "positionDelta": null,
        "appliedRuleId": null,
        "matchConfidence": 0.872653621870982
      },
      {
        "selector": "footer",
        "tag": "footer",
        "ariaLabel": null,
        "semanticLabel": null,
        "bbox": {
          "x": 0.0,
          "y": 820.0,
          "width": 1280.0,
          "height": 80.0
        },
        "status": "unchanged",
        "mode": "strict",
        "diffPixelCount": null,
        "diffPercentage": null,
        "dimensionDelta": null,
        "positionDelta": null,
        "appliedRuleId": null,
        "matchConfidence": 1.0
      }
    ],
    "blockResults": null,
    "ignoredPixels": null,
    "effectiveTotalPixels": null,
    "staleRules": null,
    "aiAnalysis": null,
    "baselineHeight": 900.0,
    "diffBBox": null
  },
  "images": {
    "baselinePng": null,
    "testPng": null,
    "diffPng": "fixtures/images/synthetic-0273_diff.png",
    "baselineDomMap": null,
    "testDomMap": null
  },
  "runContext": {
    "runId": "run-synthetic-0273",
    "createdAt": "2026-01-12T09:00:00Z",
    "trigger": "ci",
    "environmentId": null,
    "pageType": null,
    "envIsProd": true,
    "ci": {
      "commitSha": "350115fabce481be",
      "branch": "feature/237",
      "prNumber": null,
      "prTitle": null,
      "isMainBranch": true,
      "jiraKey": null
    },
    "siblingResults": [
      {
        "scenario": "contact",
        "viewport": "desktop",
        "browser": "firefox",
        "status": "fail",
        "misMatchPercentage": 20.460820437235732,
        "diffPixels": 1000.0,
        "totalPixels": 1152000.0,
        "dimensions": {
          "width": 1280.0,
          "height": 900.0
        },
        "hasContentRules": false,
        "shiftRegions": null,
        "hasShift": null,
        "elementResults": null,
        "blockResults": null,
        "ignoredPixels": null,
        "effectiveTotalPixels": null,
        "staleRules": null,
        "aiAnalysis": null,
        "baselineHeight": null,
        "diffBBox": null
      },
      {
        "scenario": "contact",
        "viewport": "desktop",
        "browser": "webkit",
        "status": "fail",
        "misMatchPercentage": 23.129240078905692,
        "diffPixels": 1000.0,
        "totalPixels": 1152000.0,
        "dimensions": {
          "width": 1280.0,
          "height": 900.0
        },
        "hasContentRules": false,
        "shiftRegions": null,
        "hasShift": null,
        "elementResults": null,
        "blockResults": null,
        "ignoredPixels": null,
        "effectiveTotalPixels": null,
        "staleRules": null,
        "aiAnalysis": null,
        "baselineHeight": null,
        "diffBBox": null
      },
      {
        "scenario": "home",
        "viewport": "desktop",
        "browser": "chromium",
        "status": "fail",
        "misMatchPercentage": 24.813140592814435,
        "diffPixels": 1000.0,
        "totalPixels": 1152000.0,
        "dimensions": {
          "width": 1280.0,
          "height": 900.0
        },
        "hasContentRules": false,
        "shiftRegions": null,
        "hasShift": null,
        "elementResults": null,
        "blockResults": null,
        "ignoredPixels": null,
        "effectiveTotalPixels": null,
        "staleRules": null,
        "aiAnalysis": null,
        "baselineHeight": null,
        "diffBBox": {
          "x": 0.0,
          "y": 0.0,
          "width": 1280.0,
          "height": 226.0
        }
      },
      {
        "scenario": "about",
        "viewport": "desktop",
        "browser": "chromium",
        "status": "fail",
        "misMatchPercentage": 17.361004614228968,
        "diffPixels": 1000.0,
        "totalPixels": 1152000.0,
        "dimensions": {
          "width": 1280.0,
          "height": 900.0
        },
        "hasContentRules": false,
        "shiftRegions": null,
        "hasShift": null,
        "elementResults": null,
        "blockResults": null,
        "ignoredPixels": null,
        "effectiveTotalPixels": null,
        "staleRules": null,
        "aiAnalysis": null,
        "baselineHeight": null,
        "diffBBox": {
          "x": 0.0,
          "y": 0.0,
          "width": 1280.0,
          "height": 226.0
        }
      },
      {
        "scenario": "pricing",
        "viewport": "desktop",
        "browser": "chromium",
        "status": "fail",
        "misMatchPercentage": 22.12671830237838,
        "diffPixels": 1000.0,
        "totalPixels": 1152000.0,
        "dimensions": {
          "width": 1280.0,
          "height": 900.0
        },
        "hasContentRules": false,
        "shiftRegions": null,
        "hasShift": null,
        "elementResults": null,
        "blockResults": null,
        "ignoredPixels": null,
        "effectiveTotalPixels": null,
        "staleRules": null,
        "aiAnalysis": null,
        "baselineHeight": null,
        "diffBBox": {
          "x": 0.0,
          "y": 0.0,
          "width": 1280.0,
          "height": 226.0
        }
      },
      {
        "scenario": "blog",
        "viewport": "desktop",
        "browser": "chromium",
        "status": "fail",
        "misMatchPercentage": 27.094798336283233,
        "diffPixels": 1000.0,
        "totalPixels": 1152000.0,
        "dimensions": {
          "width": 1280.0,
          "height": 900.0
        },
        "hasContentRules": false,
        "shiftRegions": null,
        "hasShift": null,
        "elementResults": null,
        "blockResults": null,
        "ignoredPixels": null,
        "effectiveTotalPixels": null,
        "staleRules": null,
        "aiAnalysis": null,
        "baselineHeight": null,
        "diffBBox": {
          "x": 0.0,
          "y": 0.0,
          "width": 1280.0,
          "height": 226.0
        }
      }
    ],
    "scenarioConfig": null
  },
  "intentSignals": {
    "github": {
      "commitChangedSinceBaseline": true,
      "prFilesChanged": 27,
      "uiFilesChanged": true,
      "cssLinesChanged": 601,
      "prTitleType": "style",
      "prHasDesignLabel": true,
      "changedFilesMatchPage": true
    },
    "jira": null,
    "figma": {
      "figmaDesignChangedRecently": false,
      "daysSinceFigmaVersion": 10.744300936567061,
      "figmaAlignmentBaseline": 0.78500621744428,
      "figmaAlignmentDelta": 0.028768036152291496
    }
  },
  "history": [
    {
      "runId": "hist-0",
      "createdAt": "2026-01-02T09:00:00Z",
      "misMatchPercentage": 0.9737996105879091,
      "status": "pass",
      "verdict": null,
      "diffBBox": null
    },
    {
      "runId": "hist-1",
      "createdAt": "2026-01-03T09:00:00Z",
      "misMatchPercentage": 0.6980453866258598,
      "status": "pass",
      "verdict": null,
      "diffBBox": null
    },
    {
      "runId": "hist-2",
      "createdAt": "2026-01-04T09:00:00Z",
      "misMatchPercentage": 0.71213475284417,
      "status": "fail",
      "verdict": null,
      "diffBBox": null
    },
    {
      "runId": "hist-3",
      "createdAt": "2026-01-05T09:00:00Z",
      "misMatchPercentage": 0.8766627460645684,
      "status": "pass",
      "verdict": null,
      "diffBBox": null
    },
    {
      "runId": "hist-4",
      "createdAt": "2026-01-06T09:00:00Z",
      "misMatchPercentage": 0.5447698475129746,
      "status": "fail",
      "verdict": null,
      "diffBBox": null
    },
    {
      "runId": "hist-5",
      "createdAt": "2026-01-07T09:00:00Z",
      "misMatchPercentage": 0.12528239573286037,
      "status": "pass",
      "verdict": null,
      "diffBBox": null
    },
    {
      "runId": "hist-6",
      "createdAt": "2026-01-08T09:00:00Z",
      "misMatchPercentage": 0.7157008486267261,
      "status": "pass",
      "verdict": null,
      "diffBBox": null
    },
    {
      "runId": "hist-7",
      "createdAt": "2026-01-09T09:00:00Z",
      "misMatchPercentage": 0.2405387637211393,
      "status": "pass",
      "verdict": null,
      "diffBBox": null
    },
    {
      "runId": "hist-8",
      "createdAt": "2026-01-10T09:00:00Z",
      "misMatchPercentage": 0.829102489543868,
      "status": "fail",
      "verdict": null,
      "diffBBox": null
    },
    {
      "runId": "hist-9",
      "createdAt": "2026-01-11T09:00:00Z",
      "misMatchPercentage": 0.9075938657708248,
      "status": "pass",
      "verdict": null,
      "diffBBox": null
    }
  ],
  "label": {
    "verdict": "intentional_redesign",
    "verdictSource": "synthetic",
    "verdictAt": null
  }
}